.mailmap
AUTHORS
ChangeLog
LICENSE
README.rst
catalog-info.yaml
issue_model.py
jira.cfg
pytest_jira.py
requirements.txt
setup.cfg
setup.py
tox.ini
.github/workflows/publish.yml
.github/workflows/test.yml
pytest_jira.egg-info/PKG-INFO
pytest_jira.egg-info/SOURCES.txt
pytest_jira.egg-info/dependency_links.txt
pytest_jira.egg-info/entry_points.txt
pytest_jira.egg-info/not-zip-safe
pytest_jira.egg-info/pbr.json
pytest_jira.egg-info/requires.txt
pytest_jira.egg-info/top_level.txt
tests/requirements.txt
tests/test_jira.py
tests/test_utils.py