Metadata-Version: 2.1
Name: pytest-jira
Version: 0.3.22
Summary: py.test JIRA integration plugin, using markers
Home-page: http://github.com/rhevm-qe-automation/pytest_jira
Author: James Laska
Author-email: james.laska@gmail.com
License: GPLv2
Keywords: pytest,jira,plugin
Classifier: Development Status :: 3 - Alpha
Classifier: Environment :: Plugins
Classifier: Framework :: Pytest
Classifier: Intended Audience :: Developers
Classifier: License :: OSI Approved :: GNU General Public License v2 (GPLv2)
Classifier: Operating System :: POSIX
Classifier: Programming Language :: Python
Classifier: Programming Language :: Python :: 3
Classifier: Programming Language :: Python :: 3.8
Classifier: Programming Language :: Python :: 3.9
Classifier: Programming Language :: Python :: 3.10
Classifier: Topic :: Software Development :: Testing
Classifier: Topic :: Software Development :: Quality Assurance
Classifier: Topic :: Utilities
License-File: LICENSE
